kbyai/__init__.py
kbyai/facesdk.py
kbyai/idsdk.py
kbyai-1.0.0.dist-info/LICENSE
kbyai-1.0.0.dist-info/METADATA
kbyai-1.0.0.dist-info/WHEEL
kbyai-1.0.0.dist-info/top_level.txt
kbyai-1.0.0.dist-info/RECORD
