Metadata-Version: 2.1
Name: kbyai
Version: 1.0.0
Summary: Face Liveness Detection, Face Recognition and ID Card Recognition
Author-email: KBY-AI LIMITED <contact@kby-ai.com>
Project-URL: Homepage, https://kby-ai.com/
Project-URL: Issues, https://kby-ai.com/contact-us/
Classifier: Development Status :: 4 - Beta
Classifier: License :: OSI Approved :: MIT License
Classifier: Natural Language :: English
Classifier: Programming Language :: Python :: 3
Requires-Python: >=3.8
License-File: LICENSE
Requires-Dist: requests
